odyssey_omnimcp/__init__.py
odyssey_omnimcp-0.9.6.dist-info/METADATA
odyssey_omnimcp-0.9.6.dist-info/WHEEL
odyssey_omnimcp-0.9.6.dist-info/entry_points.txt
odyssey_omnimcp-0.9.6.dist-info/RECORD
