Metadata-Version: 2.4
Name: odyssey-omnimcp
Version: 0.9.6
Summary: Add your description here
Requires-Python: >=3.13
Requires-Dist: mcp[cli]>=1.9.4
